oberon/__init__.py
oberon/__main__.py
oberon/assembler.py
oberon/bootloader.py
oberon/demo.py
oberon/disk.img
oberon/display.py
oberon/risc.py
oberon/util.py
PythonOberon-0.1.0.dist-info/LICENSE
PythonOberon-0.1.0.dist-info/METADATA
PythonOberon-0.1.0.dist-info/WHEEL
PythonOberon-0.1.0.dist-info/top_level.txt
PythonOberon-0.1.0.dist-info/RECORD
