Metadata-Version: 2.1
Name: PythonOberon
Version: 0.1.0
Summary: A hardware emulator for the Oberon RISC processor.
Home-page: https://git.sr.ht/~sforman/PythonOberon
Author: Simon Forman
Author-email: sforman@hushmail.com
License: GPLv3+
Platform: UNKNOWN
Classifier: Programming Language :: Python :: 2.7
Classifier: Development Status :: 4 - Beta
Classifier: License :: OSI Approved :: GNU General Public License v3 or later (GPLv3+)
Classifier: Operating System :: OS Independent
Classifier: Intended Audience :: Developers
Classifier: Topic :: Software Development :: Assemblers
Classifier: Topic :: Software Development :: Libraries :: pygame
Classifier: Topic :: System :: Emulators
